pretix_homepage/__init__.py
pretix_homepage/apps.py
pretix_homepage/signals.py
pretix_homepage/urls.py
pretix_homepage/views.py
pretix_homepage/locale/de/LC_MESSAGES/django.mo
pretix_homepage/locale/de/LC_MESSAGES/django.po
pretix_homepage/locale/de_Informal/.gitkeep
pretix_homepage/locale/de_Informal/LC_MESSAGES/django.mo
pretix_homepage/locale/de_Informal/LC_MESSAGES/django.po
pretix_homepage/static/pretix_homepage/.gitkeep
pretix_homepage/static/pretix_homepage/images/diptune-collage.jpg
pretix_homepage/static/pretix_homepage/images/logo_bg_white.svg
pretix_homepage/static/pretix_homepage/scss/style.scss
pretix_homepage/templates/pretix_homepage/.gitkeep
pretix_homepage/templates/pretix_homepage/about.html
pretix_homepage/templates/pretix_homepage/base.html
pretix_homepage/templates/pretix_homepage/contact.html
pretix_homepage/templates/pretix_homepage/index.html
pretix_homepage/templates/pretix_homepage/policy.html
pretix_homepage-1.0.5.dist-info/licenses/LICENSE
pretix_homepage-1.0.5.dist-info/METADATA
pretix_homepage-1.0.5.dist-info/WHEEL
pretix_homepage-1.0.5.dist-info/entry_points.txt
pretix_homepage-1.0.5.dist-info/top_level.txt
pretix_homepage-1.0.5.dist-info/RECORD
