Metadata-Version: 2.4
Name: pretix-homepage
Version: 1.0.5
Summary: A home page for self hosted Pretix
Author-email: Diptangshu Chakrabarty <cdiptangshu@gmail.com>
Maintainer-email: Diptangshu Chakrabarty <cdiptangshu@gmail.com>
License: Apache
Project-URL: homepage, https://github.com/cdiptangshu/pretix-homepage
Project-URL: repository, https://github.com/cdiptangshu/pretix-homepage
Keywords: pretix
License-File: LICENSE
Dynamic: license-file
